CHANGELOG.txt
LICENCE.txt
MANIFEST.in
README.txt
setup.py
Parker.egg-info/SOURCES.txt
Parker.egg-info/dependency_links.txt
Parker.egg-info/top_level.txt
Parker_X.egg-info/PKG-INFO
Parker_X.egg-info/SOURCES.txt
Parker_X.egg-info/dependency_links.txt
Parker_X.egg-info/top_level.txt
basiccalculator/__init__.py