Metadata-Version: 2.1
Name: Parker-X
Version: 0.0.1
Summary: A very basic Module
Home-page: UNKNOWN
Author: Parker
Author-email: harshrawat096@gmail.com
License: MIT
Keywords: cal
Platform: UNKNOWN
Classifier: Development Status :: 5 - Production/Stable
Classifier: Intended Audience :: Education
Classifier: Operating System :: Microsoft :: Windows :: Windows 10
Classifier: License :: OSI Approved :: MIT License
Classifier: Programming Language :: Python :: 3
License-File: LICENCE.txt
